sgram/__init__.py
sgram/clients.py
sgram/string.py
sgram-0.0.2.dist-info/LICENSE
sgram-0.0.2.dist-info/METADATA
sgram-0.0.2.dist-info/WHEEL
sgram-0.0.2.dist-info/top_level.txt
sgram-0.0.2.dist-info/RECORD
